pumml/__init__.py
pumml/learners.py
pumml/pupredict.py
pumml-0.0.2.dist-info/LICENSE
pumml-0.0.2.dist-info/METADATA
pumml-0.0.2.dist-info/WHEEL
pumml-0.0.2.dist-info/top_level.txt
pumml-0.0.2.dist-info/RECORD
