Metadata-Version: 2.1
Name: pumml
Version: 0.0.2
Summary: Positive and Unlabeled Materials Machine Learning (pumml) is a code that uses semi-supervised positive and unlabeled (PU) machine learning to classify materials when data is incomplete and only examples of 'positive' materials are available.
Home-page: https://github.com/ncfrey/pumml
Author: Nathan C. Frey, Jin Wang
Author-email: n.frey@seas.upenn.edu
Maintainer: Nathan C. Frey
License: UNKNOWN
Keywords: VASP,machine,learning,materials,science,DFT,synthesis
Platform: UNKNOWN
Classifier: Programming Language :: Python :: 3
Classifier: Programming Language :: Python :: 3.6
Classifier: Intended Audience :: Science/Research
Classifier: License :: OSI Approved :: MIT License
Classifier: Operating System :: OS Independent
Classifier: Topic :: Scientific/Engineering :: Information Analysis
Classifier: Topic :: Scientific/Engineering :: Physics
Classifier: Topic :: Scientific/Engineering :: Chemistry
Classifier: Topic :: Software Development :: Libraries :: Python Modules
Requires-Python: >=3.6
Requires-Dist: matplotlib (>=3.1.1)
Requires-Dist: monty (>=2.0.4)
Requires-Dist: numpy (==1.19.4)
Requires-Dist: pandas (==1.1.4)
Requires-Dist: scikit-learn (==0.23.2)
Requires-Dist: scipy (>=1.3.0)
Requires-Dist: seaborn (>=0.9.0)
Requires-Dist: matminer (==0.6.3)
Requires-Dist: pymatgen (==2020.11.11)
